dotmatrix/__init__.py
dotmatrix/_types.py
dotmatrix/algorithms.py
dotmatrix/displays/__init__.py
dotmatrix/displays/block.py
dotmatrix/displays/braille.py
dotmatrix/displays/unit.py
dotmatrix/matrix.py
dotmatrix/py.typed
dotmatrix-0.2.0.dist-info/LICENSE
dotmatrix-0.2.0.dist-info/WHEEL
dotmatrix-0.2.0.dist-info/METADATA
dotmatrix-0.2.0.dist-info/RECORD
