Metadata-Version: 2.1
Name: dotmatrix
Version: 0.2.0
Summary: A pixel matrix rendered using braille characters.
Home-page: https://github.com/timfi/dotmatrix
License: GPL-2.0-or-later
Author: Tim Fischer
Author-email: me@timfi.com
Requires-Python: >=3.7,<4.0
Classifier: Development Status :: 3 - Alpha
Classifier: License :: OSI Approved :: GNU General Public License v2 or later (GPLv2+)
Classifier: Operating System :: OS Independent
Classifier: Programming Language :: Python :: 3
Classifier: Programming Language :: Python :: 3.10
Classifier: Programming Language :: Python :: 3.7
Classifier: Programming Language :: Python :: 3.8
Classifier: Programming Language :: Python :: 3.9
Classifier: Topic :: Utilities
Classifier: Typing :: Typed
